nova_scheduler_filters/__init__.py
nova_scheduler_filters/failure_domain_filter.py
nova_scheduler_filters/tests/unit/__init__.py
nova_scheduler_filters/tests/unit/test_failure_domain_filter.py
nova_scheduler_filters-0.1.0.dist-info/AUTHORS
nova_scheduler_filters-0.1.0.dist-info/METADATA
nova_scheduler_filters-0.1.0.dist-info/WHEEL
nova_scheduler_filters-0.1.0.dist-info/pbr.json
nova_scheduler_filters-0.1.0.dist-info/top_level.txt
nova_scheduler_filters-0.1.0.dist-info/RECORD
