Metadata-Version: 2.1
Name: nova-scheduler-filters
Version: 0.1.0
Summary: Additional filters for the OpenStack Nova scheduler
Home-page: https://vexxhost.github.io/nova-scheduler-filters/
Author: VEXXHOST, Inc.
Author-email: support@vexxhost.com
License: UNKNOWN
Project-URL: Bug Tracker, https://github.com/vexxhost/nova-scheduler-filters/issues
Project-URL: Documentation, https://vexxhost.github.io/nova-scheduler-filters/
Project-URL: Source Code, https://github.com/vexxhost/nova-scheduler-filters
Platform: UNKNOWN
Classifier: Development Status :: 5 - Production/Stable
Classifier: Environment :: OpenStack
Classifier: Intended Audience :: Information Technology
Classifier: Intended Audience :: System Administrators
Classifier: License :: OSI Approved :: Apache Software License
Classifier: Operating System :: POSIX :: Linux
Classifier: Programming Language :: Python
Classifier: Programming Language :: Python :: 3
Classifier: Programming Language :: Python :: 3.10
Classifier: Programming Language :: Python :: 3.11
Classifier: Programming Language :: Python :: 3 :: Only
Classifier: Programming Language :: Python :: Implementation :: CPython
Requires-Python: >=3.8
Requires-Dist: nova
